pygressbar.py
pygressbar-0.1.0.dist-info/DESCRIPTION.rst
pygressbar-0.1.0.dist-info/METADATA
pygressbar-0.1.0.dist-info/pydist.json
pygressbar-0.1.0.dist-info/RECORD
pygressbar-0.1.0.dist-info/top_level.txt
pygressbar-0.1.0.dist-info/WHEEL
